[
  {
    "name": "Diagnostikzentrum f\u00fcr Kleintiere - Terminsprechstunde",
    "city": "Dresden",
    "reason": "Review snippet: \"They were able to help us inEnglish.\"...",
    "website": "https://www.tagesklinik-kleintiere.de/"
  },
  {
    "name": "VetPraxis Tierarztpraxis f\u00fcr Kleintiere prakt. Tierarzt Krzysztof Sliwinski",
    "city": "Dresden",
    "reason": "Review snippet: \"He also speaksEnglish:)\"...",
    "website": "http://www.vetpraxis-dresden.de/"
  },
  {
    "name": "Animal Hospital Dresden Heath",
    "city": "Dresden",
    "reason": "Website contains English keywords",
    "website": "https://avetia-dresden.de/"
  },
  {
    "name": "LUNAVET",
    "city": "Dresden",
    "reason": "Website contains English keywords",
    "website": "https://luna-vet.de/"
  },
  {
    "name": "Tierarztpraxis Vockert",
    "city": "Dresden",
    "reason": "Website contains English keywords",
    "website": "https://tierarzt-vockert.de/"
  },
  {
    "name": "Kleintierpraxis Benitz",
    "city": "Dresden",
    "reason": "Review snippet: \"Also theyspeak English.\"...",
    "website": "http://www.kleintierpraxis-benitz.de/"
  },
  {
    "name": "Small animal practice at the Gro\u00dfer Garten - skin veterinarian",
    "city": "Dresden",
    "reason": "Website contains English keywords",
    "website": "http://hauttierarzt-dresden.de/"
  },
  {
    "name": "Wolf & Tiger Tierarztpraxis Dresden am Goldenen Reiter",
    "city": "Dresden",
    "reason": "Review snippet: \"They spoke perfectEnglish, which made everything ...",
    "website": "https://www.wolfandtiger.de/locations/dresden/"
  },
  {
    "name": "Kleintierpraxis Katrin & Andr\u00e9 Schneider",
    "city": "Dresden",
    "reason": "Website contains English keywords",
    "website": "http://www.tierarzt-in-dresden.de/"
  },
  {
    "name": "Tierarztpraxis Am Wilden Mann",
    "city": "Dresden",
    "reason": "Website contains English keywords",
    "website": "https://www.tierarzt-wildermann.de/"
  },
  {
    "name": "Kleintierpraxis Dr. Katja Niekler",
    "city": "Dresden",
    "reason": "Website contains English keywords",
    "website": "https://www.kleintierpraxis-niekler.de/"
  },
  {
    "name": "Kleintierzentrum am Waldpark",
    "city": "Dresden",
    "reason": "Review snippet: \"English speakingis a great advantage personally f...",
    "website": "http://www.tierarzt-dresden-waldpark.de/"
  },
  {
    "name": "Tierarztpraxis Dresden Cosch\u00fctz I Tier\u00e4rztin Angela Eissner",
    "city": "Dresden",
    "reason": "Website contains English keywords",
    "website": "https://www.tierarztpraxis-dresden-coschuetz.de/"
  },
  {
    "name": "Dr.med.vet. Wolfgang B\u00fcttner veterinarian",
    "city": "Dresden",
    "reason": "Website contains English keywords",
    "website": "https://dr.fressnapf.de/tierarzt/dresden/drmedvet-wolfgang-buettner-tierarzt/"
  },
  {
    "name": "Astrid Ehme Tierarztpraxis",
    "city": "Dresden",
    "reason": "Website contains English keywords",
    "website": "https://tierarztpraxis-ehme-wachwitz.de/"
  },
  {
    "name": "PET/CT",
    "city": "Dresden",
    "reason": "Website contains English keywords",
    "website": "https://www.klinikum-dresden.de/zentren/medizinische-zentren/medizinisches-versorgungszentrum-mvz/nuklearmedizin"
  },
  {
    "name": "Tierarztpraxis Dr. Nachtigall",
    "city": "Dresden",
    "reason": "Website contains English keywords",
    "website": "http://www.tierarztpraxis-nachtigall.de/"
  },
  {
    "name": "Tierpraxis Lunavet",
    "city": "Dresden",
    "reason": "Website contains English keywords",
    "website": "https://www.luna-vet.de/"
  },
  {
    "name": "Veterinary clinic at Nordring",
    "city": "Nuremberg",
    "reason": "Website contains English keywords",
    "website": "http://www.xn--tierklinik-nrnberg-x6b.de/"
  },
  {
    "name": "Medivet N\u00fcrnberg",
    "city": "Nuremberg",
    "reason": "Website contains English keywords",
    "website": "https://www.medivetgroup.com/de-de/tierarzt/nuernberg/"
  },
  {
    "name": "Tierarztpraxis Dr. Julia Probst",
    "city": "Nuremberg",
    "reason": "Website contains English keywords",
    "website": "http://www.tierarzt-langwasser.de/"
  },
  {
    "name": "Tier\u00e4rztliche Praxis f\u00fcr Augenheilkunde Dr. Kerstin Leuzinger",
    "city": "Nuremberg",
    "reason": "Website contains English keywords",
    "website": "http://www.vet-augen.de/"
  },
  {
    "name": "Specialist veterinary practice Janka Dietz",
    "city": "Nuremberg",
    "reason": "Website contains English keywords",
    "website": "http://www.dietz.vet/"
  },
  {
    "name": "Tierarzt Praxis Probst",
    "city": "Nuremberg",
    "reason": "Website contains English keywords",
    "website": "http://www.tierarzt-probst.de/"
  },
  {
    "name": "Clinic of Small Animal Surgery and Reproduction",
    "city": "Munich",
    "reason": "Website contains English keywords",
    "website": "http://www.chir.vetmed.uni-muenchen.de/"
  },
  {
    "name": "Kleintierklinik der LMU M\u00fcnchen",
    "city": "Munich",
    "reason": "Website contains English keywords",
    "website": "https://www.med.vetmed.uni-muenchen.de/index.html"
  },
  {
    "name": "Kleintierklinik Dr. Lutz",
    "city": "Munich",
    "reason": "Website contains English keywords",
    "website": "https://www.kleintierklinik-lutz.vet/"
  },
  {
    "name": "Tierarztpraxis Christian Kie\u00dfling",
    "city": "Munich",
    "reason": "Website contains English keywords",
    "website": "https://www.tierarzt-rotkreuzplatz.de/"
  },
  {
    "name": "Center for Small Animal Medicine Munich",
    "city": "Munich",
    "reason": "Website contains English keywords",
    "website": "https://www.zk-muc.de/"
  },
  {
    "name": "Tierarzt Dipl. Vet. Med. Michael Umanski | Tierarztpraxis in M\u00fcnchen",
    "city": "Munich",
    "reason": "Website contains English keywords",
    "website": "http://www.tierarzt-umanski.de/"
  },
  {
    "name": "AniCura Tierklinik Haar",
    "city": "Munich",
    "reason": "Website contains English keywords",
    "website": "https://www.anicura.de/tierklinik-haar/"
  },
  {
    "name": "aktion tier Tierrettung M\u00fcnchen e.V.",
    "city": "Munich",
    "reason": "Website contains English keywords",
    "website": "http://www.tierrettungmuenchen.de/"
  },
  {
    "name": "Tier\u00e4rztliches Augenzentrum M\u00fcnchen \u2013 Dr. Jens Fritsche & Kollegen",
    "city": "Munich",
    "reason": "Website contains English keywords",
    "website": "http://www.tier-augenarzt.de/"
  },
  {
    "name": "Tierklinik Oberhaching",
    "city": "Munich",
    "reason": "Website contains English keywords",
    "website": "http://www.tierklinik-oberhaching.de/"
  },
  {
    "name": "Veterinary practice in Franziskanerhof Dr. Christina Sacher",
    "city": "Munich",
    "reason": "Website contains English keywords",
    "website": "http://www.tierarztpraxis-im-franziskanerhof.de/"
  },
  {
    "name": "Dr. Andrea Hollmann",
    "city": "Munich",
    "reason": "Website contains English keywords",
    "website": "https://www.tierarztpraxis-hollmann.de/"
  },
  {
    "name": "Tierarzt M\u00fcnchen, Dr. med. vet. Klaus Sommer",
    "city": "Munich",
    "reason": "Website contains English keywords",
    "website": "http://www.tierarzt-sommer.de/"
  },
  {
    "name": "Dr. med.vet. Annabelle Culas",
    "city": "Munich",
    "reason": "Website contains English keywords",
    "website": "https://www.tierarztpraxis-culas.de/"
  },
  {
    "name": "Tierarztpraxis Moosach Dr. Bader-Mechler",
    "city": "Munich",
    "reason": "Website contains English keywords",
    "website": "http://www.tierarzt-muenchen-moosach.de/"
  },
  {
    "name": "Dr. med. vet. Peter Baumann",
    "city": "Munich",
    "reason": "Website contains English keywords",
    "website": "http://www.kleintierpraxis-muenchen.de/"
  },
  {
    "name": "Tierarztpraxis Michaela Gu\u00dfmann",
    "city": "Munich",
    "reason": "Website contains English keywords",
    "website": "http://tierarzt-gussmann.de/index.html"
  },
  {
    "name": "Tier\u00e4rztliche Gemeinschaftspraxis Dr. F. Fiederling und Dr. T. Ludwig",
    "city": "Munich",
    "reason": "Website contains English keywords",
    "website": "https://www.pasinger-tierarztpraxis.de/"
  },
  {
    "name": "Tierarztpraxis Dr. Heubeck",
    "city": "Munich",
    "reason": "Website contains English keywords",
    "website": "http://www.tierarztpraxis-heubeck.de/"
  },
  {
    "name": "Kleintierpraxis | Dr. Jutta Herrle | M\u00fcnchen",
    "city": "Munich",
    "reason": "Website contains English keywords",
    "website": "https://tierarzt-allach.de/"
  },
  {
    "name": "Tier\u00e4rzte W\u00fcrmtal",
    "city": "Munich",
    "reason": "Website contains English keywords",
    "website": "https://www.tieraerzte-wuermtal.de/"
  },
  {
    "name": "Veterin\u00e4ramt I Kreisverwaltungsreferat (KVR)",
    "city": "Munich",
    "reason": "Website contains English keywords",
    "website": "http://www.muenchen.de/dienstleistungsfinder/muenchen/1080981"
  }
]